pyaxis/__init__.py
pyaxis/pyaxis.py
pyaxis/test/__init__.py
pyaxis/test/test.py
pyaxis-0.2.0.dist-info/METADATA
pyaxis-0.2.0.dist-info/RECORD
pyaxis-0.2.0.dist-info/WHEEL
pyaxis-0.2.0.dist-info/top_level.txt
