Metadata-Version: 2.1
Name: pyaxis
Version: 0.2.0
Summary: Library to handle PC-Axis data in python using pandas DataFrames.
Home-page: https://github.com/icane/pyaxis
Author: Instituto Cántabro de Estadística
Author-email: icane@cantabria.es
License: Apache License 2.0
Keywords: pcaxis,statistics,dataframe,converter
Platform: UNKNOWN
Classifier: Development Status :: 4 - Beta
Classifier: Environment :: Console
Classifier: Intended Audience :: Developers
Classifier: Intended Audience :: Science/Research
Classifier: License :: OSI Approved :: Apache Software License
Classifier: Operating System :: MacOS :: MacOS X
Classifier: Operating System :: Microsoft :: Windows
Classifier: Operating System :: POSIX
Classifier: Programming Language :: Python
Classifier: Topic :: Scientific/Engineering :: Information Analysis
Classifier: Topic :: Software Development :: Libraries
Requires-Dist: numpy
Requires-Dist: requests
Requires-Dist: pandas
